shapeshift/__init__.py
shapeshift/compat.py
shapeshift/formatters.py
shapeshift/generic.py
shapeshift-0.3.5.dist-info/LICENSE
shapeshift-0.3.5.dist-info/METADATA
shapeshift-0.3.5.dist-info/WHEEL
shapeshift-0.3.5.dist-info/top_level.txt
shapeshift-0.3.5.dist-info/RECORD
